MANIFEST.in
setup.py
opps/__init__.py
opps/promos/__init__.py
opps/promos/admin.py
opps/promos/forms.py
opps/promos/models.py
opps/promos/search_indexes.py
opps/promos/tasks.py
opps/promos/tests.py
opps/promos/urls.py
opps/promos/utils.py
opps/promos/views.py
opps/promos/migrations/0001_initial.py
opps/promos/migrations/0002_new_urls.py
opps/promos/migrations/0003_auto__add_field_promo_countdown_enabled.py
opps/promos/migrations/__init__.py
opps/promos/templates/promos/actives.html
opps/promos/templates/promos/promo_closed.html
opps/promos/templates/promos/promo_detail.html
opps/promos/templates/promos/promo_list.html
opps/promos/templatetags/__init__.py
opps/promos/templatetags/promos_tags.py
opps_promos.egg-info/PKG-INFO
opps_promos.egg-info/SOURCES.txt
opps_promos.egg-info/dependency_links.txt
opps_promos.egg-info/namespace_packages.txt
opps_promos.egg-info/requires.txt
opps_promos.egg-info/top_level.txt